LICENSE
MANIFEST.in
README.md
README.rst
setup.py
test/__init__.py
test/test_simivec.py
torch_simivec/__init__.py
torch_simivec/simivec.py
torch_simivec.egg-info/PKG-INFO
torch_simivec.egg-info/SOURCES.txt
torch_simivec.egg-info/dependency_links.txt
torch_simivec.egg-info/requires.txt
torch_simivec.egg-info/top_level.txt
torch_simivec.egg-info/zip-safe