Metadata-Version: 2.1
Name: torch-simivec
Version: 0.1.2
Summary: Input Embedding Training as Similarity Learning Problem (SimiVec)
Home-page: http://github.com/ulf1/torch-simivec
Author: Ulf Hamster
Author-email: 554c46@gmail.com
License: Apache License 2.0
Platform: UNKNOWN
Requires-Python: >=3.6
License-File: LICENSE
